Workbook

Sheet CALCULADORA
C1: CÉLULA AUTOMÁTICA - NÃO ALTERAR
B3: ETAPA | C3: ITEM | E3: VALOR | F3: OBSERVAÇÕES | H3: TABELA AUXILIAR - RESOLUÇÃO DE FRETE SEM CIRCULAR
B4: PRODUTO | C4: PESO (Kg) UN. | E4: 0.1 | H4: Faixa de Preço | I4: Limite Inferior | J4: Limite Superior | K4: Frete (por peso) | L4: PV Resultante | M4: PV na Faixa? | N4: Frete Correto
C5: COMP. EMB. PRIMÁRIA (cm) | E5: 26.6 | H5: R$ 0 a R$ 18,99 | I5: 0 | J5: 18.99 | K5: =IF($E$17="Minha",INDEX(FRETE!C40:C68,MATCH($E$4,{0,0.3,0.5,1,1.5,2,3,4,5,6,7,8,9,11,13,15,17,20,25,30,40,50,60,70,80,90,100,125,150},1)),INDEX(FRETE!C7:C35,MATCH($E$4,{0,0.3,0.5,1,1.5,2,3,4,5,6,7,8,9,11,13,15,17,20,25,30,40,50,60,70,80,90,100,125,150},1))) -> 5.65 | L5: =SUM($E$12,K5,$E$16)/(1-(SUM($E$19,$E$20,$E$25,$E$30,$E$13,$E$28,((1+$E$29)^($E$31/30))-1))) -> 20.213101 | M5: =IF(AND(L5>=I5,L5<=J5),"SIM","NÃO") -> NÃO | N5: =IFERROR(INDEX(K5:K12,MATCH("SIM",M5:M12,0)),K12) -> 6.55
C6: LARG. EMB. PRIMÁRIA (cm) | E6: 13.1 | H6: R$ 19 a R$ 48,99 | I6: 19 | J6: 48.99 | K6: =IF($E$17="Minha",INDEX(FRETE!C40:C68,MATCH($E$4,{0,0.3,0.5,1,1.5,2,3,4,5,6,7,8,9,11,13,15,17,20,25,30,40,50,60,70,80,90,100,125,150},1)),INDEX(FRETE!D7:D35,MATCH($E$4,{0,0.3,0.5,1,1.5,2,3,4,5,6,7,8,9,11,13,15,17,20,25,30,40,50,60,70,80,90,100,125,150},1))) -> 6.55 | L6: =SUM($E$12,K6,$E$16)/(1-(SUM($E$19,$E$20,$E$25,$E$30,$E$13,$E$28,((1+$E$29)^($E$31/30))-1))) -> 22.013504 | M6: =IF(AND(L6>=I6,L6<=J6),"SIM","NÃO") -> SIM
C7: ALT. EMB. PRIMÁRIA (cm) | E7: 3.6 | H7: R$ 49 a R$ 78,99 | I7: 49 | J7: 78.99 | K7: =IF($E$17="Minha",INDEX(FRETE!C40:C68,MATCH($E$4,{0,0.3,0.5,1,1.5,2,3,4,5,6,7,8,9,11,13,15,17,20,25,30,40,50,60,70,80,90,100,125,150},1)),INDEX(FRETE!E7:E35,MATCH($E$4,{0,0.3,0.5,1,1.5,2,3,4,5,6,7,8,9,11,13,15,17,20,25,30,40,50,60,70,80,90,100,125,150},1))) -> 7.75 | L7: =SUM($E$12,K7,$E$16)/(1-(SUM($E$19,$E$20,$E$25,$E$30,$E$13,$E$28,((1+$E$29)^($E$31/30))-1))) -> 24.414042 | M7: =IF(AND(L7>=I7,L7<=J7),"SIM","NÃO") -> NÃO
C8: QTD | E8: 350 | H8: R$ 79 a R$ 99,99 | I8: 79 | J8: 99.99 | K8: =INDEX(FRETE!F7:F35,MATCH(E4,{0,0.3,0.5,1,1.5,2,3,4,5,6,7,8,9,11,13,15,17,20,25,30,40,50,60,70,80,90,100,125,150},1)) -> 12.35 | L8: =SUM($E$12,K8,$E$16)/(1-(SUM($E$19,$E$20,$E$25,$E$30,$E$13,$E$28,((1+$E$29)^($E$31/30))-1))) -> 33.616104 | M8: =IF(AND(L8>=I8,L8<=J8),"SIM","NÃO") -> NÃO
C9: CUSTO UN. C/ IPI | E9: 3.9 | H9: R$ 100 a R$ 119,99 | I9: 100 | J9: 119.99 | K9: =INDEX(FRETE!G7:G35,MATCH(E4,{0,0.3,0.5,1,1.5,2,3,4,5,6,7,8,9,11,13,15,17,20,25,30,40,50,60,70,80,90,100,125,150},1)) -> 14.35 | L9: =SUM($E$12,K9,$E$16)/(1-(SUM($E$19,$E$20,$E$25,$E$30,$E$13,$E$28,((1+$E$29)^($E$31/30))-1))) -> 37.617001 | M9: =IF(AND(L9>=I9,L9<=J9),"SIM","NÃO") -> NÃO
C10: SUBST. TRIBUT | E10: 36.5 | H10: R$ 120 a R$ 149,99 | I10: 120 | J10: 149.99 | K10: =INDEX(FRETE!H7:H35,MATCH(E4,{0,0.3,0.5,1,1.5,2,3,4,5,6,7,8,9,11,13,15,17,20,25,30,40,50,60,70,80,90,100,125,150},1)) -> 16.45 | L10: =SUM($E$12,K10,$E$16)/(1-(SUM($E$19,$E$20,$E$25,$E$30,$E$13,$E$28,((1+$E$29)^($E$31/30))-1))) -> 41.817942 | M10: =IF(AND(L10>=I10,L10<=J10),"SIM","NÃO") -> NÃO
C11: CUSTO TOTAL | E11: =(E9*E8)+E10 -> 1401.5 | H11: R$ 150 a R$ 199,99 | I11: 150 | J11: 199.99 | K11: =INDEX(FRETE!I7:I35,MATCH(E4,{0,0.3,0.5,1,1.5,2,3,4,5,6,7,8,9,11,13,15,17,20,25,30,40,50,60,70,80,90,100,125,150},1)) -> 18.45 | L11: =SUM($E$12,K11,$E$16)/(1-(SUM($E$19,$E$20,$E$25,$E$30,$E$13,$E$28,((1+$E$29)^($E$31/30))-1))) -> 45.818839 | M11: =IF(AND(L11>=I11,L11<=J11),"SIM","NÃO") -> NÃO
C12: CUSTO UN. FINAL | E12: =E11/E8 -> 4.0042857 | H12: A partir de R$ 200 | I12: 200 | J12: 99999 | K12: =INDEX(FRETE!J7:J35,MATCH(E4,{0,0.3,0.5,1,1.5,2,3,4,5,6,7,8,9,11,13,15,17,20,25,30,40,50,60,70,80,90,100,125,150},1)) -> 20.95 | L12: =SUM($E$12,K12,$E$16)/(1-(SUM($E$19,$E$20,$E$25,$E$30,$E$13,$E$28,((1+$E$29)^($E$31/30))-1))) -> 50.81996 | M12: =IF(AND(L12>=I12,L12<=J12),"SIM","NÃO") -> NÃO
C13: CUSTO OPERACIONAL | E13: 0 | F13: Frete interno, embalagem e mão de obra, aramazenagem própria - padrão 1%
B14: MERCADO LIVRE | C14: TIPO LOGÍSTICA | E14: Full
C15: TAMANHO | E15: =IF(AND(E5<=25,E6<=15,E7<=12,E4<=18),"PEQUENO",IF(AND(E5<=51,E6<=36,E7<=28,E4<=18),"MÉDIO",IF(AND(E5<=7,E6<=6,E7<=6,E4<=18),"GRANDE","EXTRAGRANDE"))) -> MÉDIO
C16: CUSTO UN. ARMAZENAGEM | E16: =IF(E14="Full",((E8/2)*(IF(E15="pequeno",FULL!C5,IF(E15="médio",FULL!C8,IF(E15="grande",FULL!C11,FULL!C14))))*E31)/E8,0) -> 0.45
C17: FRETE POR CONTA | E17: Cliente
C18: FRETE FINAL | E18: =N5 -> 6.55 | F18: =IF(AND(E22>19,E22<79,E17<>"Minha"),"FRETE GRÁTIS PADRÃO",IF(AND(E22<=19,E17<>"Minha"),"FRETE PAGO PELO CLIENTE",IF(AND(E22>79,E17="Minha"),"MUDAR PARA FRETE POR CONTA DO CLIENTE",IF(E17="Minha","FRETE GRÁTIS RÁPIDO","FRETE GRÁTIS RÁPIDO")))) -> FRETE GRÁTIS PADRÃO
C19: CLÁSSICO | E19: =IF(C19="clássico",0.13,0.18) -> 0.13
C20: ROAS | D20: 3.57 | E20: =1/D20 -> 0.28011204
C21: INVEST. MKT | E21: =E36*E20 -> 2158.1867 | F21: ="INVESTIMENTO EM ADS - R$"&ROUND(E21/E31,0)&" ORÇAMENTO DIARIO PARA VENDER TUDO EM 60D - OU MAIOR PARA ACELERAR" -> INVESTIMENTO EM ADS - R$36 ORÇAMENTO DIARIO PARA VENDER TUDO EM 60D - OU MAIOR PARA ACELERAR
B22: COMERCIAL | C22: PV | E22: =SUM(E12,E18,E16)/(1-(SUM(E19,E20,E25,E30,E13,E28,(((1+E29)^(E31/30))-1)))) -> 22.013504 | F22: ="Preço para 10 unidades ou mais R$ "&ROUND(E22*0.95,2)&" - 5% de desconto" -> Preço para 10 unidades ou mais R$ 20,91 - 5% de desconto
C23: MARGEM BRUTA | E23: =(E22-E9)/E22 -> 0.82283602
C24: MULTIPLICADOR | E24: =E22/E9 -> 5.6444883
B25: FISCAL/FINANCEIRO | C25: IMPOSTOS SIMPLES | E25: 0.06
C26: ICMS PRÓPRIO | E26: 0.04
C27: ICMS DESTINO | E27: 0.04
C28: DIFAL | E28: =E27-E26 -> 0
C29: CUSTO FINANCEIRO a.m | E29: 0 | F29: Padrão - 2%
C30: MARGEM LÍQ. % | E30: 0.03
C31: GIRO (d) | E31: 60 | F31: =ROUND((E8/120),0)&" VENDAS POR DIA COMO META - 4 MESES RETIRAR!" -> 3 VENDAS POR DIA COMO META - 4 MESES RETIRAR!
C32: MARGEM LIQ. ABSOLUTA | E32: =E22*E30*E8 -> 231.1418
C33: MARGEM LIQ. ABSOLUTA UN. | E33: =E30*E22 -> 0.66040513
C34: ROI | E34: =E32/E11 -> 0.16492458
C35: ROI a.a | E35: =(1+E34)^(365/E31)-1 -> 1.5311138 | F35: SELIC 15% a.a ...
C36: FATURAMENTO TOTAL | E36: =E22*E8 -> 7704.7265

Sheet FULL
B2: Custos pelo serviço de armazenamento | H2: Custos pelo serviço de retirada ou descarte
B4: Tamanho do produto | C4: Tarifa diária por unidade | H4: Volume total do estoque | I4: Custo por retirar | J4: Custo por descartar
B5: Pequeno | C5: 0.007 | I5: Aproveite os descontos em m³ para grandes volumes
B6: (Até 12 x 15 x 25 cm e peso de até 18 kg.) | H6: Até 0,01 m³ | I6: 98 | J6: 1
B7: Ex.: tablet. | H7: De 0,01 a 0,025 m³ | I7: Entre R$ 80 e R$ 201 | J7: Entre R$ 1 e R$ 2
B8: Médio | C8: 0.015 | H8: De 0,025 a 0,05 m³ | I8: Entre R$ 121 e R$ 242 | J8: Entre R$ 1 e R$ 3
B9: (Até 28 x 36 x 51 cm e peso de até 18 kg.) | H9: De 0,05 a 0,1 m³ | I9: Entre R$ 185 e R$ 370 | J9: Entre R$ 2 e R$ 5
B10: Ex.: cafeteira. | H10: De 0,1 a 0,25 m³ | I10: Entre R$ 258 e R$ 645 | J10: Entre R$ 4 e R$ 9
B11: Grande | C11: 0.05 | H11: De 0,25 a 0,50 m³ | I11: Entre R$ 475 e R$ 950 | J11: Entre R$ 7 e R$ 14
B12: (Até 60 x 60 x 70 cm e peso de até 18 kg.) | H12: De 0,50 a 1 m³ | I12: Entre R$ 740 e R$ 1.480 | J12: Entre R$ 12 e R$ 24
B13: Ex.: micro-ondas. | H13: De 1 a 2 m³ | I13: Entre R$ 1.300 e R$ 2.600 | J13: Entre R$ 18 e R$ 36
B14: Extragrande | C14: 0.107 | I14: O m³ custa R$ 1.121 | J14: O m³ custa R$ 18
B15: (Mais de 60 x 60 x 70 cm e/ou peso maior que 18 kg.) | H15: De 2 a 5 m³ | I15: Entre R$ 2.200 e R$ 5.500 | J15: Entre R$ 34 e R$ 85
B16: Ex.: balde de tinta. | I16: O m³ custa R$ 1.020 | J16: O m³ custa R$ 17
H17: De 5 a 10 m³ | I17: Entre R$ 4.950 e R$ 9.900 | J17: Entre R$ 70 e R$ 140
B18: Custos por estoque antigo no Full | I18: O m³ custa R$ 910 | J18: O m³ custa R$ 17
H19: De 10 a 20 m³ | I19: Entre R$ 8.400 e R$ 16.800 | J19: Entre R$ 140 e R$ 280
B20: Tamanho do produto | C20: Tempo de armazenamento | I20: O m³ custa R$ 796 | J20: O m³ custa R$ 14
C21: Até 4 meses | D21: De 4 a 6 meses | E21: De 6 a 12 meses | F21: Mais de 12 meses | H21: De 20 a 50 m³ | I21: Entre R$ 13.540 e R$ 33.850 | J21: Entre R$ 120 e R$ 300
B22: Pequeno | C22: Sem custo | D22: R$ 1,00 | E22: R$ 12,00 | F22: R$ 28,00 | I22: O m³ custa R$ 576 | J22: O m³ custa R$ 6
B23: Mede até 12 x 15 x 25 cm e pesa até 18 kg | H23: Mais de 50 m³ | I23: A partir de R$ 29.500 | J23: A partir de R$ 300
B24: Ex.: tablet. | I24: O m³ custa R$ 583 | J24: O m³ custa R$ 6
B25: Médio | C25: Sem custo | D25: R$ 2,00 | E25: R$ 15,00 | F25: R$ 32,00
B26: Mede até 28 x 36 x 51 cm e pesa até 18 kg
B27: Ex.: cafeteira.
B28: Grande | C28: Sem custo | D28: R$ 6,00 | E28: R$ 37,00 | F28: R$ 85,00
B29: Mede até 60 x 60 x 70 cm e pesa até 18 kg
B30: Ex.: micro-ondas.
B31: Extragrande | C31: Sem custo | D31: R$ 8,00 | E31: R$ 47,00 | F31: R$ 131,00
B32: Mede mais que 60 x 60 x 70 cm e/ou pesa mais que 18 kg
B33: Ex.: balde de tinta.

Sheet FRETE
B1: https://www.mercadolivre.com.br/ajuda/custos-envio-reputacao-verde-mercado-lider_40538
B2: Custos de envio para MercadoLíder, reputação verde ou sem reputação
B3: Em anúncios de R$ 19 a R$ 78,99, o Mercado Livre oferece frete grátis padrão.
B4: Em anúncios a partir de R$ 79, você oferece frete grátis e rápido.
B6: Peso* | C6: R$ 0 a R$ 18,99* | D6: R$ 19 a R$ 48,99 | E6: R$ 49 a R$ 78,99 | F6: R$ 79 a R$ 99,99 | G6: R$ 100 a R$ 119,99 | H6: R$ 120 a R$ 149,99 | I6: R$ 150 a R$ 199,99 | J6: A partir de R$ 200
B7: Até 0,3 kg | C7: 5.65 | D7: 6.55 | E7: 7.75 | F7: 12.35 | G7: 14.35 | H7: 16.45 | I7: 18.45 | J7: 20.95
B8: De 0,3 a 0,5 kg | C8: 5.95 | D8: 6.65 | E8: 7.85 | F8: 13.25 | G8: 15.45 | H8: 17.65 | I8: 19.85 | J8: 22.55
B9: De 0,5 a 1 kg | C9: 6.05 | D9: 6.75 | E9: 7.95 | F9: 13.85 | G9: 16.15 | H9: 18.45 | I9: 20.75 | J9: 23.65
B10: De 1 a 1,5 kg | C10: 6.15 | D10: 6.85 | E10: 8.05 | F10: 14.15 | G10: 16.45 | H10: 18.85 | I10: 21.15 | J10: 24.65
B11: De 1,5 a 2 kg | C11: 6.25 | D11: 6.95 | E11: 8.15 | F11: 14.45 | G11: 16.85 | H11: 19.25 | I11: 21.65 | J11: 24.65
B12: De 2 a 3 kg | C12: 6.35 | D12: 7.95 | E12: 8.55 | F12: 15.75 | G12: 18.35 | H12: 21.05 | I12: 23.65 | J12: 26.25
B13: De 3 a 4 kg | C13: 6.45 | D13: 8.15 | E13: 8.95 | F13: 17.05 | G13: 19.85 | H13: 22.65 | I13: 25.55 | J13: 28.35
B14: De 4 a 5 kg | C14: 6.55 | D14: 8.35 | E14: 9.75 | F14: 18.45 | G14: 21.55 | H14: 24.65 | I14: 27.75 | J14: 30.75
B15: De 5 a 6 kg | C15: 6.65 | D15: 8.55 | E15: 9.95 | F15: 25.45 | G15: 28.55 | H15: 32.65 | I15: 35.75 | J15: 39.75
B16: De 6 a 7 kg | C16: 6.75 | D16: 8.75 | E16: 10.15 | F16: 27.05 | G16: 31.05 | H16: 36.05 | I16: 40.05 | J16: 44.05
B17: De 7 a 8 kg | C17: 6.85 | D17: 8.95 | E17: 10.35 | F17: 28.85 | G17: 33.65 | H17: 38.45 | I17: 43.25 | J17: 48.05
B18: De 8 a 9 kg | C18: 6.95 | D18: 9.15 | E18: 10.55 | F18: 29.65 | G18: 34.55 | H18: 39.55 | I18: 44.45 | J18: 49.35
... B35: Mais de 150 kg | C35: 8.75 | D35: 12.95 | E35: 14.35 | F35: 166.15 | G35: 192.45 | H35: 217.55 | I35: 242.55 | J35: 261.95
B37: Custos por oferecer frete grátis e rápido para produtos abaixo de R$ 79 (opcional)
B39: Peso | C39: R$ 0 a R$ 78,99*
B40: Até 0,3 kg | C40: 12.35
B41: De 0,3 a 0,5 kg | C41: 13.25
B42: De 0,5 a 1 kg | C42: 13.85
B43: De 1 a 1,5 kg | C43: 14.15
B44: De 1,5 a 2 kg | C44: 14.45
B45: De 2 a 3 kg | C45: 15.75
B46: De 3 a 4 kg | C46: 17.05
B47: De 4 a 5 kg | C47: 18.45
B48: De 5 a 6 kg | C48: 25.45
B49: De 6 a 7 kg | C49: 27.05
B50: De 7 a 8 kg | C50: 28.85
B51: De 8 a 9 kg | C51: 29.65
... B68: Mais de 150 kg | C68: 166.15

Sheet WEB_APP_SPEC
A1: Web App Blueprint — Calculadora Mercado Livre
A2: Objetivo | B2: Transformar a planilha em app web responsivo para precificação, margem e ROI | C2: Decisões de compra/anúncio com dados salvos por produto e cenário | D2: CALCULADORA!C4:E36
A4: Seção | B4: Item | C4: Especificação | D4: Mapeamento / Observação
A5: Stack | B5: Framework | C5: Next.js App Router + TypeScript | D5: Full-stack, rotas, server actions/API e deploy simples
A6: Stack | B6: UI/UX | C6: shadcn/ui + Tailwind CSS + lucide-react + Recharts | D6: Componentes editáveis, cards, sidebar, charts e data tables
A7: Stack | B7: Forms/Validação | C7: React Hook Form + Zod | D7: Inputs com validação, máscaras BRL/%/kg/cm e mensagens claras
A8: Stack | B8: Dados | C8: Prisma ORM + PostgreSQL inicialmente | D8: Banco definitivo pode ser trocado depois via repository layer
A9: Stack | B9: Auth/Futuro | C9: NextAuth/Auth.js ou Clerk/Supabase Auth | D9: Preparar usuário, empresa e permissões
A10: UX | B10: Dashboard | C10: Cards com PV, margem líquida, ROI, faturamento, investimento ADS e status do frete | D10: CALCULADORA!E21:E36
A11: UX | B11: Wizard de Produto | C11: Produto → Custos → Logística → Comercial → Fiscal/Financeiro → Resultado | D11: CALCULADORA!E4:E31
A12: UX | B12: Precificador | C12: Formulário à esquerda e resultado vivo à direita | D12: Atualização dinâmica antes de salvar
A13: UX | B13: Cenários | C13: Salvar simulações por produto: Conservador/Base/Agressivo | D13: Novo conceito: histórico de simulações
A14: UX | B14: Tabelas Admin | C14: Editar frete, Full, comissões e impostos | D14: FRETE!B6:J68; FULL!B2:J33
... A52: Definition of Done | B52: MVP | C52: Cálculo bate com planilha em casos-teste, UI responsiva, dados mockáveis, schema preparado, histórico opcional | D52: Checklist de entrega
A54: Developer Handoff — Instruções para IA Fullstack
A55: Como usar este handoff | B55: Leia esta seção junto com o blueprint acima antes de codar | C55: A IA/dev deve implementar o MVP seguindo arquitetura, UX, cálculo, dados e testes abaixo | D55: Não pule testes de cálculo contra a planilha
A57: Bloco | B57: Instrução | C57: Detalhe de Implementação | D57: Critério de Aceite
A58: Missão | B58: Construir um web app de precificação Mercado Livre baseado na planilha | C58: Transformar a lógica de CALCULADORA, FRETE e FULL em aplicação web com UI moderna, dados persistíveis e motor de cálculo testável | D58: Usuário consegue calcular preço, salvar produto/cenário e ver resultado confiável
A59: Princípio | B59: Não tratar a planilha como UI final | C59: A planilha é a fonte inicial de regras de negócio; o app deve virar produto SaaS simples, intuitivo e expansível | D59: Interface não deve parecer uma tabela Excel copiada
A60: Princípio | B60: Separar cálculo, UI e persistência | C60: Motor de cálculo puro em TypeScript; UI consome função/API; banco apenas armazena entradas, tarifas e resultados | D60: Cálculo pode rodar em teste unitário sem banco e sem React
A61: Princípio | B61: Preparar dados dinâmicos | C61: Tarifas, impostos, comissões, parâmetros de Full e cenários não devem ficar hardcoded na UI | D61: Mudanças de tarifa são feitas em tabela/admin ou seed, não no componente
A62: Princípio | B62: Manter auditabilidade | C62: Todo resultado deve guardar inputs usados, versão/vigência das tarifas e timestamp | D62: Histórico permite explicar por que um PV foi calculado
A63: Stack Obrigatória | B63: Next.js + TypeScript | C63: Usar App Router, TypeScript strict, componentes server/client quando fizer sentido | D63: Projeto roda com npm/pnpm dev sem erros de tipo
A64: Stack Obrigatória | B64: shadcn/ui + Tailwind CSS | C64: Usar componentes shadcn para Card, Button, Input, Select, Tabs, Sheet, Dialog, Table, Badge, Tooltip e Form | D64: UI consistente, bonita e fácil de ajustar
A65: Stack Obrigatória | B65: React Hook Form + Zod | C65: Zod define schemas de formulário e schemas de cálculo; React Hook Form controla inputs | D65: Validação clara para BRL, %, kg, cm, dias, ROAS e quantidade
A66: Stack Obrigatória | B66: Prisma + banco relacional | C66: Começar com PostgreSQL ou SQLite para desenvolvimento local; manter Prisma provider fácil de trocar | D66: Schema versionado e migrations funcionando
A67: Stack Recomendada | B67: Recharts | C67: Usar para breakdown de custos, comparação de cenários e ROI vs margem | D67: Gráficos aparecem no dashboard e tela de resultado
... A144: Prompt para outra IA | B144: Primeira entrega esperada | C144: Entregar estrutura do projeto, Prisma schema, seed inicial, calculatePricing() com testes, e tela /pricing/new funcional com preview do resultado. | D144: Primeiro PR/MVP técnico
